Heppi-0.4.dist-info/DESCRIPTION.rst
Heppi-0.4.dist-info/METADATA
Heppi-0.4.dist-info/RECORD
Heppi-0.4.dist-info/WHEEL
Heppi-0.4.dist-info/entry_points.txt
Heppi-0.4.dist-info/metadata.json
Heppi-0.4.dist-info/top_level.txt
heppi/__init__.py
heppi/heppi.py
heppi/performance.py
heppi/settings.py
