Metadata-Version: 2.0
Name: Heppi
Version: 0.4
Summary: High Energy Physics Plotting Interface
Home-page: https://github.com/yhaddad/Heppi
Author: Yacine Haddad
Author-email: yhaddad@cern.ch
License: ISCL
Download-URL: https://github.com/yhaddad/Heppi/tarball/0.4
Keywords: Heppi,heppi
Platform: UNKNOWN
Classifier: Development Status :: 2 - Pre-Alpha
Classifier: Intended Audience :: Developers
Classifier: Environment :: Console
Classifier: Intended Audience :: Science/Research
Classifier: License :: OSI Approved :: ISC License (ISCL)
Classifier: Natural Language :: English
Classifier: Topic :: Scientific/Engineering :: Visualization
Classifier: Topic :: Utilities
Classifier: Programming Language :: Python :: 2.7
Classifier: Programming Language :: Python :: 3
Classifier: Programming Language :: Python :: 3.3
Classifier: Programming Language :: Python :: 3.4
Classifier: Programming Language :: Python :: 3.5
Requires-Dist: jsmin
Requires-Dist: jsonmerge
Requires-Dist: progressbar
Requires-Dist: termcolor
